{
  "Susie": [
    {
      "name": "Bitcoin",
      "ticker": "BTC_USDT",
      "exchange": "Crypto",
      "category": "Crypto",
      "currency": "USD",
      "qty": 1.7511246,
      "price": 68597.0234375,
      "valuation": 180819549.0989836
    },
    {
      "name": "Ethereum",
      "ticker": "ETH_USDT",
      "exchange": "Crypto",
      "category": "Crypto",
      "currency": "USD",
      "qty": 1.10666755,
      "price": 2136.52099609375,
      "valuation": 3559159.102224179
    },
    {
      "name": "KRW",
      "ticker": "KRW",
      "exchange": "—",
      "category": "Cash",
      "currency": "KRW",
      "qty": 52920854.0,
      "price": 1.0,
      "valuation": 52920854.0
    },
    {
      "name": "TIGER CD1년금리액티브(합성)",
      "ticker": "475630",
      "exchange": "KRX",
      "category": "Cash",
      "currency": "KRW",
      "qty": 64.0,
      "price": 1062580.0,
      "valuation": 68005120.0
    },
    {
      "name": "USDT",
      "ticker": "USDT",
      "exchange": "—",
      "category": "Cash",
      "currency": "USD",
      "qty": 10.89383819,
      "price": 1.0,
      "valuation": 16398.494627407
    },
    {
      "name": "KINDEX KRX금현물",
      "ticker": "411060",
      "exchange": "KRX",
      "category": "Gold",
      "currency": "KRW",
      "qty": 2365.0,
      "price": 31825.0,
      "valuation": 75266125.0
    },
    {
      "name": "TIGER KOSDAQ150",
      "ticker": "232080",
      "exchange": "KRX",
      "category": "Kor Stock",
      "currency": "KRW",
      "qty": 2003.0,
      "price": 19660.0,
      "valuation": 39378980.0
    },
    {
      "name": "ACE 미국S&P500",
      "ticker": "360200",
      "exchange": "KRX",
      "category": "US Stock",
      "currency": "KRW",
      "qty": 807.0,
      "price": 24820.0,
      "valuation": 20029740.0
    },
    {
      "name": "KODEX 미국나스닥100(TR)",
      "ticker": "379810",
      "exchange": "KRX",
      "category": "US Stock",
      "currency": "KRW",
      "qty": 2481.0,
      "price": 23945.0,
      "valuation": 59407545.0
    },
    {
      "name": "ACE 미국장기채액티브",
      "ticker": "476760",
      "exchange": "KRX",
      "category": "US Bonds",
      "currency": "KRW",
      "qty": 7981.0,
      "price": 10270.0,
      "valuation": 81964870.0
    }
  ],
  "D&B": [],
  "Jintae": [
    {
      "name": "Bitcoin",
      "ticker": "BTC_USDT",
      "exchange": "Crypto",
      "category": "Crypto",
      "currency": "USD",
      "qty": 0.21670934,
      "price": 68597.0234375,
      "valuation": 22377211.27573579
    },
    {
      "name": "Ethereum",
      "ticker": "ETH_USDT",
      "exchange": "Crypto",
      "category": "Crypto",
      "currency": "USD",
      "qty": 2.63407606,
      "price": 2136.52099609375,
      "valuation": 8471465.33292659
    },
    {
      "name": "KODEX KOFR금리액티브(합성)",
      "ticker": "423160",
      "exchange": "KRX",
      "category": "Cash",
      "currency": "KRW",
      "qty": 1327.0,
      "price": 110645.0,
      "valuation": 146825915.0
    },
    {
      "name": "TIGER MSCI US 리츠(합성H)",
      "ticker": "182480",
      "exchange": "KRX",
      "category": "Cash",
      "currency": "KRW",
      "qty": 4095.0,
      "price": 12620.0,
      "valuation": 51678900.0
    },
    {
      "name": "KRW",
      "ticker": "KRW",
      "exchange": "—",
      "category": "Cash",
      "currency": "KRW",
      "qty": 1663406.0,
      "price": 1.0,
      "valuation": 1663406.0
    },
    {
      "name": "유비케어",
      "ticker": "032620",
      "exchange": "KOSDAQ",
      "category": "Kor Stock",
      "currency": "KRW",
      "qty": 101579.0,
      "price": 4050.0,
      "valuation": 411394950.0
    },
    {
      "name": "KODEX 미국나스닥100(TR)",
      "ticker": "379810",
      "exchange": "KRX",
      "category": "US Stock",
      "currency": "KRW",
      "qty": 1650.0,
      "price": 23945.0,
      "valuation": 39509250.0
    },
    {
      "name": "KINDEX S&P500 3070 Blend",
      "ticker": "438080",
      "exchange": "KRX",
      "category": "US Bonds",
      "currency": "KRW",
      "qty": 5600.0,
      "price": 14060.0,
      "valuation": 78736000.0
    },
    {
      "name": "ACE 미국장기채액티브",
      "ticker": "476760",
      "exchange": "KRX",
      "category": "US Bonds",
      "currency": "KRW",
      "qty": 8145.0,
      "price": 10270.0,
      "valuation": 83649150.0
    }
  ],
  "Hyunhee": [
    {
      "name": "Bitcoin",
      "ticker": "BTC_USDT",
      "exchange": "Crypto",
      "category": "Crypto",
      "currency": "USD",
      "qty": 0.18921629,
      "price": 68597.0234375,
      "valuation": 19538303.6935136
    },
    {
      "name": "Ethereum",
      "ticker": "ETH_USDT",
      "exchange": "Crypto",
      "category": "Crypto",
      "currency": "USD",
      "qty": 1.42834823,
      "price": 2136.52099609375,
      "valuation": 4593717.963403097
    },
    {
      "name": "TIGER MSCI US 리츠(합성H)",
      "ticker": "182480",
      "exchange": "KRX",
      "category": "Cash",
      "currency": "KRW",
      "qty": 4118.0,
      "price": 14060.0,
      "valuation": 57899080.0
    },
    {
      "name": "KRW",
      "ticker": "KRW",
      "exchange": "—",
      "category": "Cash",
      "currency": "KRW",
      "qty": 2054914.0,
      "price": 1.0,
      "valuation": 2054914.0
    },
    {
      "name": "KODEX CD금리액티브(합성)",
      "ticker": "459580",
      "exchange": "KRX",
      "category": "Cash",
      "currency": "KRW",
      "qty": 4.0,
      "price": 1073470.0,
      "valuation": 4293880.0
    },
    {
      "name": "KINDEX KRX금현물",
      "ticker": "411060",
      "exchange": "KRX",
      "category": "Gold",
      "currency": "KRW",
      "qty": 642.0,
      "price": 31825.0,
      "valuation": 20431650.0
    },
    {
      "name": "TIGER KOSDAQ150",
      "ticker": "232080",
      "exchange": "KRX",
      "category": "Kor Stock",
      "currency": "KRW",
      "qty": 1030.0,
      "price": 19660.0,
      "valuation": 20249800.0
    },
    {
      "name": "KODEX 미국나스닥100(TR)",
      "ticker": "379810",
      "exchange": "KRX",
      "category": "US Stock",
      "currency": "KRW",
      "qty": 2616.0,
      "price": 23945.0,
      "valuation": 62640120.0
    },
    {
      "name": "ACE 미국장기채액티브",
      "ticker": "476760",
      "exchange": "KRX",
      "category": "US Bonds",
      "currency": "KRW",
      "qty": 4185.0,
      "price": 10270.0,
      "valuation": 42979950.0
    }
  ],
  "Total": [],
  "Dirac & Broglie": [
    {
      "name": "KRW",
      "ticker": "KRW",
      "exchange": "—",
      "category": "Cash",
      "currency": "KRW",
      "qty": 1021815.0,
      "price": 1.0,
      "valuation": 1021815.0
    },
    {
      "name": "TIGER CD1년금리액티브(합성)",
      "ticker": "475630",
      "exchange": "KRX",
      "category": "Cash",
      "currency": "KRW",
      "qty": 769.0,
      "price": 1062580.0,
      "valuation": 817124020.0
    },
    {
      "name": "USD",
      "ticker": "USD",
      "exchange": "—",
      "category": "Cash",
      "currency": "USD",
      "qty": 4883.0,
      "price": 1.0,
      "valuation": 7358095.063842772
    },
    {
      "name": "STRC",
      "ticker": "STRC",
      "exchange": "NASDAQ",
      "category": "Cash",
      "currency": "USD",
      "qty": 5335.0,
      "price": 99.83,
      "valuation": 802553817.7845519
    },
    {
      "name": "KINDEX KRX금현물",
      "ticker": "411060",
      "exchange": "KRX",
      "category": "Gold",
      "currency": "KRW",
      "qty": 12757.0,
      "price": 31825.0,
      "valuation": 405991525.0
    },
    {
      "name": "KBSTAR 200 Total Return",
      "ticker": "361580",
      "exchange": "KRX",
      "category": "Kor Stock",
      "currency": "KRW",
      "qty": 4112.0,
      "price": 46640.0,
      "valuation": 191783680.0
    },
    {
      "name": "TIGER KOSDAQ150",
      "ticker": "232080",
      "exchange": "KRX",
      "category": "Kor Stock",
      "currency": "KRW",
      "qty": 7509.0,
      "price": 19660.0,
      "valuation": 147626940.0
    },
    {
      "name": "KoAct 코스닥액티브",
      "ticker": "0163Y0",
      "exchange": "KRX",
      "category": "Kor Stock",
      "currency": "KRW",
      "qty": 3500.0,
      "price": 12300.0,
      "valuation": 43050000.0
    },
    {
      "name": "QQQM",
      "ticker": "QQQM",
      "exchange": "NASDAQ",
      "category": "US Stock",
      "currency": "USD",
      "qty": 2092.0,
      "price": 237.6199951171875,
      "valuation": 749071602.1899072
    },
    {
      "name": "SCHD",
      "ticker": "SCHD",
      "exchange": "NYSE Arca",
      "category": "US Stock",
      "currency": "USD",
      "qty": 8342.0,
      "price": 30.68000030517578,
      "valuation": 385659661.0986501
    },
    {
      "name": "VTIP",
      "ticker": "VTIP",
      "exchange": "NASDAQ",
      "category": "US Bonds",
      "currency": "USD",
      "qty": 3580.0,
      "price": 49.95000076293945,
      "valuation": 269461793.4689257
    },
    {
      "name": "VGLT",
      "ticker": "VGLT",
      "exchange": "NASDAQ",
      "category": "US Bonds",
      "currency": "USD",
      "qty": 3663.0,
      "price": 55.36000061035156,
      "valuation": 305570676.077513
    }
  ],
  "_prev_totals": {
    "Susie": 578618617.4937584,
    "Dirac & Broglie": 4122069911.510628,
    "Jintae": 842141354.2514498,
    "Hyunhee": 233912091.93198088
  }
}