{
  "Susie": [
    {
      "name": "Bitcoin",
      "ticker": "BTC_USDT",
      "exchange": "Crypto",
      "category": "Crypto",
      "currency": "USD",
      "qty": 1.7511246,
      "price": 70925.8984375,
      "valuation": 185641867.8431974
    },
    {
      "name": "Ethereum",
      "ticker": "ETH_USDT",
      "exchange": "Crypto",
      "category": "Crypto",
      "currency": "USD",
      "qty": 1.10666755,
      "price": 2150.4033203125,
      "valuation": 3557059.5186609384
    },
    {
      "name": "KRW",
      "ticker": "KRW",
      "exchange": "—",
      "category": "Cash",
      "currency": "KRW",
      "qty": 52920854.0,
      "price": 1.0,
      "valuation": 52920854.0
    },
    {
      "name": "TIGER CD1년금리액티브(합성)",
      "ticker": "475630",
      "exchange": "KRX",
      "category": "Cash",
      "currency": "KRW",
      "qty": 64.0,
      "price": 1061935.0,
      "valuation": 67963840.0
    },
    {
      "name": "USDT",
      "ticker": "USDT",
      "exchange": "—",
      "category": "Cash",
      "currency": "USD",
      "qty": 10.89383819,
      "price": 1.0,
      "valuation": 16283.019942593
    },
    {
      "name": "KINDEX KRX금현물",
      "ticker": "411060",
      "exchange": "KRX",
      "category": "Gold",
      "currency": "KRW",
      "qty": 2365.0,
      "price": 29940.0,
      "valuation": 70808100.0
    },
    {
      "name": "TIGER KOSDAQ150",
      "ticker": "232080",
      "exchange": "KRX",
      "category": "Kor Stock",
      "currency": "KRW",
      "qty": 2003.0,
      "price": 19995.0,
      "valuation": 40049985.0
    },
    {
      "name": "ACE 미국S&P500",
      "ticker": "360200",
      "exchange": "KRX",
      "category": "US Stock",
      "currency": "KRW",
      "qty": 807.0,
      "price": 24670.0,
      "valuation": 19908690.0
    },
    {
      "name": "KODEX 미국나스닥100(TR)",
      "ticker": "379810",
      "exchange": "KRX",
      "category": "US Stock",
      "currency": "KRW",
      "qty": 2481.0,
      "price": 23995.0,
      "valuation": 59531595.0
    },
    {
      "name": "ACE 미국장기채액티브",
      "ticker": "476760",
      "exchange": "KRX",
      "category": "US Bonds",
      "currency": "KRW",
      "qty": 7981.0,
      "price": 10165.0,
      "valuation": 81126865.0
    }
  ],
  "Dirac & Broglie": [
    {
      "name": "KRW",
      "ticker": "KRW",
      "exchange": "—",
      "category": "Cash",
      "currency": "KRW",
      "qty": 1717620.0,
      "price": 1.0,
      "valuation": 1717620.0
    },
    {
      "name": "TIGER CD1년금리액티브(합성)",
      "ticker": "475630",
      "exchange": "KRX",
      "category": "Cash",
      "currency": "KRW",
      "qty": 774.0,
      "price": 1061935.0,
      "valuation": 821937690.0
    },
    {
      "name": "USD",
      "ticker": "USD",
      "exchange": "—",
      "category": "Cash",
      "currency": "USD",
      "qty": 4883.0,
      "price": 1.0,
      "valuation": 7294127.883056641
    },
    {
      "name": "STRC",
      "ticker": "STRC",
      "exchange": "NASDAQ",
      "category": "Cash",
      "currency": "USD",
      "qty": 5335.0,
      "price": 99.83,
      "valuation": 795576861.8323121
    },
    {
      "name": "KINDEX KRX금현물",
      "ticker": "411060",
      "exchange": "KRX",
      "category": "Gold",
      "currency": "KRW",
      "qty": 12757.0,
      "price": 29940.0,
      "valuation": 381944580.0
    },
    {
      "name": "KBSTAR 200 Total Return",
      "ticker": "361580",
      "exchange": "KRX",
      "category": "Kor Stock",
      "currency": "KRW",
      "qty": 4112.0,
      "price": 47330.0,
      "valuation": 194620960.0
    },
    {
      "name": "TIGER KOSDAQ150",
      "ticker": "232080",
      "exchange": "KRX",
      "category": "Kor Stock",
      "currency": "KRW",
      "qty": 7509.0,
      "price": 19995.0,
      "valuation": 150142455.0
    },
    {
      "name": "KoAct 코스닥액티브",
      "ticker": "0163Y0",
      "exchange": "KRX",
      "category": "Kor Stock",
      "currency": "KRW",
      "qty": 3500.0,
      "price": 12485.0,
      "valuation": 43697500.0
    },
    {
      "name": "QQQM",
      "ticker": "QQQM",
      "exchange": "NASDAQ",
      "category": "US Stock",
      "currency": "USD",
      "qty": 2092.0,
      "price": 242.0700073242188,
      "valuation": 756465824.7875379
    },
    {
      "name": "SCHD",
      "ticker": "SCHD",
      "exchange": "NYSE Arca",
      "category": "US Stock",
      "currency": "USD",
      "qty": 8342.0,
      "price": 30.54000091552734,
      "valuation": 380562402.5626986
    },
    {
      "name": "VTIP",
      "ticker": "VTIP",
      "exchange": "NASDAQ",
      "category": "US Bonds",
      "currency": "USD",
      "qty": 3580.0,
      "price": 49.81999969482422,
      "valuation": 266424031.76126328
    },
    {
      "name": "VGLT",
      "ticker": "VGLT",
      "exchange": "NASDAQ",
      "category": "US Bonds",
      "currency": "USD",
      "qty": 3663.0,
      "price": 55.11999893188477,
      "valuation": 301600993.7075492
    }
  ],
  "Jintae": [
    {
      "name": "Bitcoin",
      "ticker": "BTC_USDT",
      "exchange": "Crypto",
      "category": "Crypto",
      "currency": "USD",
      "qty": 0.21670934,
      "price": 70925.8984375,
      "valuation": 22973994.344358206
    },
    {
      "name": "Ethereum",
      "ticker": "ETH_USDT",
      "exchange": "Crypto",
      "category": "Crypto",
      "currency": "USD",
      "qty": 2.63407606,
      "price": 2150.4033203125,
      "valuation": 8466467.93077099
    },
    {
      "name": "KODEX KOFR금리액티브(합성)",
      "ticker": "423160",
      "exchange": "KRX",
      "category": "Cash",
      "currency": "KRW",
      "qty": 1327.0,
      "price": 110810.0,
      "valuation": 147044870.0
    },
    {
      "name": "TIGER MSCI US 리츠(합성H)",
      "ticker": "182480",
      "exchange": "KRX",
      "category": "Cash",
      "currency": "KRW",
      "qty": 4095.0,
      "price": 12705.0,
      "valuation": 52026975.0
    },
    {
      "name": "KRW",
      "ticker": "KRW",
      "exchange": "—",
      "category": "Cash",
      "currency": "KRW",
      "qty": 1663406.0,
      "price": 1.0,
      "valuation": 1663406.0
    },
    {
      "name": "유비케어",
      "ticker": "032620",
      "exchange": "KOSDAQ",
      "category": "Kor Stock",
      "currency": "KRW",
      "qty": 22305.0,
      "price": 3935.0,
      "valuation": 87770175.0
    },
    {
      "name": "KODEX 미국나스닥100(TR)",
      "ticker": "379810",
      "exchange": "KRX",
      "category": "US Stock",
      "currency": "KRW",
      "qty": 1650.0,
      "price": 23995.0,
      "valuation": 39591750.0
    },
    {
      "name": "KINDEX S&P500 3070 Blend",
      "ticker": "438080",
      "exchange": "KRX",
      "category": "US Bonds",
      "currency": "KRW",
      "qty": 5600.0,
      "price": 13935.0,
      "valuation": 78036000.0
    },
    {
      "name": "ACE 미국장기채액티브",
      "ticker": "476760",
      "exchange": "KRX",
      "category": "US Bonds",
      "currency": "KRW",
      "qty": 8145.0,
      "price": 10165.0,
      "valuation": 82793925.0
    }
  ],
  "Hyunhee": [
    {
      "name": "Bitcoin",
      "ticker": "BTC_USDT",
      "exchange": "Crypto",
      "category": "Crypto",
      "currency": "USD",
      "qty": 0.18921629,
      "price": 70925.8984375,
      "valuation": 20059375.273444343
    },
    {
      "name": "Ethereum",
      "ticker": "ETH_USDT",
      "exchange": "Crypto",
      "category": "Crypto",
      "currency": "USD",
      "qty": 1.42834823,
      "price": 2150.4033203125,
      "valuation": 4591008.083217045
    },
    {
      "name": "TIGER MSCI US 리츠(합성H)",
      "ticker": "182480",
      "exchange": "KRX",
      "category": "Cash",
      "currency": "KRW",
      "qty": 4118.0,
      "price": 13935.0,
      "valuation": 57384330.0
    },
    {
      "name": "KRW",
      "ticker": "KRW",
      "exchange": "—",
      "category": "Cash",
      "currency": "KRW",
      "qty": 2054914.0,
      "price": 1.0,
      "valuation": 2054914.0
    },
    {
      "name": "KODEX CD금리액티브(합성)",
      "ticker": "459580",
      "exchange": "KRX",
      "category": "Cash",
      "currency": "KRW",
      "qty": 4.0,
      "price": 1075110.0,
      "valuation": 4300440.0
    },
    {
      "name": "KINDEX KRX금현물",
      "ticker": "411060",
      "exchange": "KRX",
      "category": "Gold",
      "currency": "KRW",
      "qty": 642.0,
      "price": 29940.0,
      "valuation": 19221480.0
    },
    {
      "name": "TIGER KOSDAQ150",
      "ticker": "232080",
      "exchange": "KRX",
      "category": "Kor Stock",
      "currency": "KRW",
      "qty": 1030.0,
      "price": 19995.0,
      "valuation": 20594850.0
    },
    {
      "name": "KODEX 미국나스닥100(TR)",
      "ticker": "379810",
      "exchange": "KRX",
      "category": "US Stock",
      "currency": "KRW",
      "qty": 2616.0,
      "price": 23995.0,
      "valuation": 62770920.0
    },
    {
      "name": "ACE 미국장기채액티브",
      "ticker": "476760",
      "exchange": "KRX",
      "category": "US Bonds",
      "currency": "KRW",
      "qty": 4185.0,
      "price": 10165.0,
      "valuation": 42540525.0
    }
  ],
  "Total": [],
  "_prev_totals": {
    "Susie": 578686349.0429783,
    "Dirac & Broglie": 4073054416.176915,
    "Jintae": 519625961.18844974,
    "Hyunhee": 232674313.58812544
  }
}